[
    {
        "name": "වසන්ත යපාබණ්ඩාර",
        "position": "පාර්ලිමේන්තු මන්ත්‍රී",
        "party": "ශ්‍රී ලංකා පොදුජන පෙරමුණ",
        "district": "මහනුවර",
        "contact_information": [
            "813154545",
            "wasantha_y@parliament.lk"
        ],
        "overall_rank": 95,
        "participated_in_parliament": 27,
        "related_subjects": [
            "නගර සැලසුම්, යටිතල පහසුකම් හා ප්‍රවාහන",
            "ජාතික උරුමයන්, මාධ්‍ය හා ක්‍රීඩා",
            "යුක්තිය, ආරක්ෂාව හා මහජන සාමය",
            "ස්වභාවික සම්පත් හා පරිසර",
            "ආර්ථික හා මුල්‍ය"
        ],
        "biography": "වසන්ත යපාබණ්ඩාර මහතා 1972-06-24 දින උපත ලබා ඇත.2020-08-20 සිට අද දක්වා ශ්‍රී ලංකා පොදුජන පෙරමුණ නියෝජනය කරමින් පාර්ලිමේන්තුවේ අසුන් ගෙන සිටී."
    }
]