[
    {
        "name": "විදුර වික්‍රමනායක",
        "position": "රාජ්‍ය අමාත්‍ය  ,  ජාතික උරුම, ප්‍රාසාංග කලා හා ග්‍රාමීය කලා ශිල්පී ප්‍රවර්ධන කටයුතු",
        "party": "ශ්‍රී ලංකා පොදුජන පෙරමුණ",
        "district": "කළුතර",
        "contact_information": [
            "342264477",
            "wickramanayaka_v@parliament.lk"
        ],
        "overall_rank": 152,
        "participated_in_parliament": 28,
        "related_subjects": [
            "ජාතික උරුමයන්, මාධ්‍ය හා ක්‍රීඩා",
            "අධ්‍යාපන",
            "සුබසාධන හා සමාජ සේවා",
            "ආණ්ඩුකරණ, පරිපාලන හා පාර්ලිමේන්තු කටයුතු",
            "ආර්ථික හා මුල්‍ය"
        ],
        "biography": "විදුර වික්‍රමනායක මහතා 1959-11-07 දින උපත ලබා ඇත.මෙතුමා Royal College, Colombo යන පාසලේ අධ්යාපනය ලබා ඇත.තම ප්‍රථම උපාධිය BSc, Agriculture, University of Philippines ලබාගෙන ඇත. ඊට අමතරව Philippines, VITARICH corporation, Consultant, Intl Institute of Rural Construction, පශ්චාත් උපාධිය ද සම්පූර්ණ කර ඇත.2020-08-20 සිට අද දක්වා ශ්‍රී ලංකා පොදුජන පෙරමුණ නියෝජනය කරමින් පාර්ලිමේන්තුවේ අසුන් ගෙන සිටී."
    }
]